Metadata-Version: 1.0
Name: P2PProxiesAuthorizer
Version: 0.0.1
Summary: P2P Proxies Authorizer
Home-page: https://rev.proxies.online
Author: Garry Lachman
Author-email: garry@lachman.co
License: UNKNOWN
Platform: UNKNOWN
